D3mel/__init__.py
D3mel/d3mel.py
D3mel/utilities/utilities.py
D3mel/utilities/utilities_gos.py
D3mel/utilities/utilities_position_map.py
D3mel/utilities/utilities_protein_complex.py
D3mel/utilities/utilities_rnaseq.py
D3mel/utilities/ExtraData/7227.tsv
D3mel-0.1.0.dist-info/METADATA
D3mel-0.1.0.dist-info/WHEEL
D3mel-0.1.0.dist-info/top_level.txt
D3mel-0.1.0.dist-info/RECORD
