Metadata-Version: 2.1
Name: D3mel
Version: 0.1.0
Summary: Data Downloader of Drosophila melanogaster
Home-page: https://github.com/JavieraQuirozO/D3mel
Author: Javiera Quiroz Olave
Author-email: javiera.quiroz@biomedica.udec.cl
License: MIT
Classifier: Development Status :: 3 - Alpha
Classifier: Intended Audience :: Science/Research
Classifier: Intended Audience :: Healthcare Industry
Classifier: License :: OSI Approved :: MIT License
Classifier: Programming Language :: Python :: 3
Requires-Dist: flybasedownloads>=3.1.1
